Metadata-Version: 1.0
Name: mapper-on-file
Version: 0.0.2
Summary: This is a mapper based on deep_mapper1. It will help you convert object from one to other based on configuration.
Home-page: https://github.com/cao5zy/mapper_on_file
Author: zongying.cao
Author-email: zongying_cao@163.com
License: MIT
Platform: UNKNOWN
